lecaps/__init__.py
Lecaps-1.0.0.dist-info/LICENSE.txt
Lecaps-1.0.0.dist-info/METADATA
Lecaps-1.0.0.dist-info/WHEEL
Lecaps-1.0.0.dist-info/top_level.txt
Lecaps-1.0.0.dist-info/RECORD
