Metadata-Version: 2.1
Name: Lecaps
Version: 1.0.0
Summary: Cotizar tasas implícitas de Lecaps
Home-page: https://github.com/EmilianoEzequielG/Lecaps
Author: Emiliano Ezequiel
Classifier: Programming Language :: Python :: 3
Classifier: License :: OSI Approved :: MIT License
Classifier: Operating System :: OS Independent
Requires-Python: >=3.6
License-File: LICENSE.txt
